{
    "run": "1",
    "cloud": "batch",
    "job_conf": "Default",
    "workflow_id": "bddcdd049e475662",
    "history_id": "c02d13a567d32d77",
    "inputs": "SRR24043307-2GB GRCh38.p14.gbff.gz",
    "metrics": {
        "model_class": "Job",
        "id": "8f7deb74beec36db",
        "history_id": "c02d13a567d32d77",
        "tool_id": "toolshed.g2.bx.psu.edu/repos/iuc/lofreq_filter/lofreq_filter/2.1.5+galaxy0",
        "state": "ok",
        "exit_code": 0,
        "create_time": "2026-03-31T13:17:33.166818",
        "update_time": "2026-03-31T16:40:34.554833",
        "galaxy_version": "26.1",
        "external_id": "galaxy-job-1774975113-42d63592",
        "handler": null,
        "job_runner_name": null,
        "command_line": "lofreq filter -i /galaxy/server/database/objects/6/1/2/dataset_61260647-9f15-4017-a0c8-350b60b43527.dat --no-defaults --verbose --print-all  -v 0 -V 0 -a 0.0 -A 0.0 -b fdr -c 0.001   -o filtered.vcf",
        "user_email": "default-user@galaxyproject.org",
        "user_id": "b9eec48891b366cf",
        "command_version": "2.1.5",
        "params": {
            "af": "{\"af_max\": \"0.0\", \"af_min\": \"0.0\"}",
            "coverage": "{\"cov_max\": \"0\", \"cov_min\": \"0\"}",
            "filter_by_type": "{\"__current_case__\": 0, \"keep_only\": \"\", \"qual\": {\"indelqual_filter\": {\"__current_case__\": 0, \"indelqual\": \"no\"}, \"snvqual_filter\": {\"__current_case__\": 0, \"snvqual\": \"no\"}}}",
            "flag_or_drop": "\"--print-all\"",
            "sb": "{\"sb_filter\": {\"__current_case__\": 2, \"sb_alpha\": \"0.001\", \"sb_compound\": true, \"sb_indels\": false, \"sb_mtc\": \"fdr\", \"strand_bias\": \"mtc\"}}",
            "__workflow_invocation_uuid__": "\"f8bb92042d0311f1acc282839cb514a4\"",
            "chromInfo": "\"/cvmfs/data.galaxyproject.org/managed/len/ucsc/?.len\"",
            "dbkey": "\"?\"",
            "__input_ext": "\"input\""
        },
        "inputs": {
            "invcf": {
                "id": "07939c0d75052580",
                "src": "hda",
                "uuid": "61260647-9f15-4017-a0c8-350b60b43527"
            }
        },
        "outputs": {
            "outvcf": {
                "id": "680422cc795d7a21",
                "src": "hda",
                "uuid": "d88bbcfa-7e46-4360-83e0-8e147de3af4f"
            }
        },
        "copied_from_job_id": null,
        "output_collections": {
            "outvcf": {
                "src": "hdca",
                "id": "b01fa5ef993b8ed3"
            }
        },
        "tool_stdout": "",
        "tool_stderr": "Skipping default settings\nAt least one type of multiple testing correction requested. Doing first pass of vcf\nMTC application completed\nSuccessful exit.\n",
        "job_stdout": "",
        "job_stderr": "",
        "stdout": "",
        "stderr": "Skipping default settings\nAt least one type of multiple testing correction requested. Doing first pass of vcf\nMTC application completed\nSuccessful exit.\n",
        "job_messages": [],
        "dependencies": [],
        "job_metrics": [
            {
                "title": "Container ID",
                "value": "quay.io/biocontainers/lofreq:2.1.5--py312ha5e83ca_15",
                "plugin": "core",
                "name": "container_id",
                "raw_value": "quay.io/biocontainers/lofreq:2.1.5--py312ha5e83ca_15"
            },
            {
                "title": "Container Type",
                "value": "docker",
                "plugin": "core",
                "name": "container_type",
                "raw_value": "docker"
            },
            {
                "title": "Cores Allocated",
                "value": "1",
                "plugin": "core",
                "name": "galaxy_slots",
                "raw_value": "1.0000000"
            },
            {
                "title": "Memory Allocated (MB)",
                "value": "15564",
                "plugin": "core",
                "name": "galaxy_memory_mb",
                "raw_value": "15564.0000000"
            },
            {
                "title": "Job Start Time",
                "value": "2026-03-31 16:40:29",
                "plugin": "core",
                "name": "start_epoch",
                "raw_value": "1774975229.0000000"
            },
            {
                "title": "Job End Time",
                "value": "2026-03-31 16:40:30",
                "plugin": "core",
                "name": "end_epoch",
                "raw_value": "1774975230.0000000"
            },
            {
                "title": "Job Runtime (Wall Clock)",
                "value": "1 second",
                "plugin": "core",
                "name": "runtime_seconds",
                "raw_value": "1.0000000"
            }
        ]
    },
    "status": "ok",
    "server": "http://34.11.12.196",
    "ref_data_size": [],
    "input_data_size": [
        503642961,
        1289376399
    ]
}